searchcake-0.0.5.dist-info/DESCRIPTION.rst
searchcake-0.0.5.dist-info/WHEEL
searchcake-0.0.5.dist-info/metadata.json
searchcake-0.0.5.dist-info/top_level.txt
searchcake-0.0.5.dist-info/RECORD
searchcake-0.0.5.dist-info/METADATA
searchcake/fdr.py
searchcake/pepidentWFapp.py
searchcake/tppWF.py
searchcake/peptideprophet.py
searchcake/spectrastrtcalib.py
searchcake/peptideIdentificationWF.py
searchcake/pepidentWF.py
searchcake/pepxmlcorrector.py
searchcake/interprophet.py
searchcake/proteinprophet.py
searchcake/spectrast2tsv2traml.py
searchcake/__init__.py
searchcake/searchWFini.py
searchcake/searchengines/myrimatch.py
searchcake/searchengines/comet.py
searchcake/searchengines/omssa.py
searchcake/searchengines/iprophetpepxml2csv.py
searchcake/searchengines/xtandem.py
searchcake/searchengines/__init__.py
searchcake/searchengines/searchenginebase.py
searchcake/searchengines/enzymes.py
searchcake/searchengines/modifications.py
