Metadata-Version: 2.0
Name: searchcake
Version: 0.0.5
Summary: tpp search workflow with peptideprophet and proteinprophet staring from mzXML files
Home-page: https://github.com/applicake-tools/searchcake
Author: ['Lorenz Blum', 'Witold Wolski']
Author-email: ['blum@id.ethz.ch', 'wewolski@gmail.com']
License: BSD
Platform: UNKNOWN
Requires-Dist: Unimod
Requires-Dist: applicake
Requires-Dist: pyteomics
Requires-Dist: ruffus
Requires-Dist: configobj
